{
  "id": "prop-003",
  "title": "Modern Home on Rosehill Lane",
  "address": "755 Rosehill Ln",
  "city": "Lawrenceville",
  "state": "GA",
  "zipCode": "30044",
  "price": 2100,
  "bedrooms": 3,
  "bathrooms": 2.5,
  "sqft": 2100,
  "type": "house",
  "status": "available",
  "featured": true,
  "description": "Stunning 3-bedroom home with modern finishes throughout. Features gourmet kitchen with granite countertops, spacious master suite, and an open floor plan perfect for entertaining. Located in a desirable Lawrenceville neighborhood with excellent schools nearby.",
  "amenities": [
    "Granite Countertops",
    "Central Air",
    "Stainless Steel Appliances",
    "Walk-in Closets",
    "Attached Garage",
    "Smart Home Features",
    "Gas Fireplace"
  ],
  "images": [
    "https://images.unsplash.com/photo-1600585154340-be6161a56a0c?w=800&q=80",
    "https://images.unsplash.com/photo-1600607687644-c7171b42498b?w=800&q=80",
    "https://images.unsplash.com/photo-1613977257363-707ba9348227?w=800&q=80"
  ],
  "yearBuilt": 2020,
  "parking": "2-car attached garage",
  "petsAllowed": true,
  "laundry": "In-unit washer/dryer"
}